bsdict/__init__.py
bsdict/bsdict.py
bsdict/bsdict_tests.py
bsdict/bslt.py
bsdict/bslt_tests.py
bsdict/farray.py
bsdict/farray_tests.py
bsdict-0.1.0.dist-info/LICENSE.txt
bsdict-0.1.0.dist-info/METADATA
bsdict-0.1.0.dist-info/WHEEL
bsdict-0.1.0.dist-info/top_level.txt
bsdict-0.1.0.dist-info/RECORD
