Metadata-Version: 2.1
Name: bsdict
Version: 0.1.0
Summary: A python dictionary where keys could be lists, dictionaris, numpy arrays, etc.
Home-page: https://github.com/andrei-dubovik/bsdict
Author: Andrei Dubovik
Author-email: andrei@dubovik.eu
License: UNKNOWN
Platform: UNKNOWN
Classifier: Programming Language :: Python :: 3
Classifier: License :: OSI Approved :: BSD License
Classifier: Operating System :: OS Independent
Requires-Python: >=3.7
